cookiesparser/__init__.py
cookiesparser/__version__.py
cookiesparser/cparser.py
cookiesparser/utils.py
cookiesparser-1.4.0.dist-info/LICENSE
cookiesparser-1.4.0.dist-info/METADATA
cookiesparser-1.4.0.dist-info/WHEEL
cookiesparser-1.4.0.dist-info/top_level.txt
cookiesparser-1.4.0.dist-info/RECORD
