Metadata-Version: 2.1
Name: cookiesparser
Version: 1.4.0
Summary: cookiesparser is a mini module for parsing cookies.
Author: Farhan Ali
Author-email: i.farhanali.dev@gmail.com
Keywords: cookies,cookie parsing,cookie management,http cookies,web development,python cookies,cookie encoder,cookie decoder,data parsing,string manipulation,mini module,farhan ali
Classifier: Programming Language :: Python :: 3
Classifier: License :: OSI Approved :: Apache Software License
Classifier: Operating System :: OS Independent
License-File: LICENSE
